libsidp/__init__.py
libsidp-0.3.4.dist-info/licenses/LICENSE
libsidp-0.3.4.dist-info/METADATA
libsidp-0.3.4.dist-info/WHEEL
libsidp-0.3.4.dist-info/top_level.txt
libsidp-0.3.4.dist-info/RECORD
