Metadata-Version: 2.4
Name: libsidp
Version: 0.3.4
Summary: Lib implementing SIDP
Author-email: Steven Wallimann <steven.wallimann@gmail.com>
License: Copyright (c) 2025 The Python Packaging Authority
Classifier: Programming Language :: Python :: 3
Classifier: Operating System :: OS Independent
Requires-Python: >=3.8
License-File: LICENSE
Requires-Dist: pydantic==2.10.4
Dynamic: license-file
